MyPackage_Bala/Modelstat.py
MyPackage_Bala/_init_.py
MyPackage_Bala/functions.py
MyPackage_Bala-0.4.dist-info/LICENSE
MyPackage_Bala-0.4.dist-info/METADATA
MyPackage_Bala-0.4.dist-info/WHEEL
MyPackage_Bala-0.4.dist-info/top_level.txt
MyPackage_Bala-0.4.dist-info/RECORD
